chemic/__init__.py
chemic/app.py
chemic/chemical_labels.py
chemic/client.py
chemic/config.py
chemic/image_classifier.py
chemic/loading_images.py
chemic/utils.py
ChemIC_ml-1.3.1.dist-info/LICENSE.md
ChemIC_ml-1.3.1.dist-info/METADATA
ChemIC_ml-1.3.1.dist-info/WHEEL
ChemIC_ml-1.3.1.dist-info/top_level.txt
ChemIC_ml-1.3.1.dist-info/RECORD
