Metadata-Version: 2.1
Name: ChemIC-ml
Version: 1.3.1
Summary: Chemical images classification project. Program for training the deep neural network model and web service for classification  chemical images
Home-page: https://github.com/ontochem/ChemIC.git
Author: Dr.Aleksei Krasnov
Author-email: a.krasnov@digital-science.com
License: MIT
Classifier: Topic :: Software Development :: Build Tools
Classifier: License :: OSI Approved :: MIT License
Classifier: Programming Language :: Python :: 3
Classifier: Programming Language :: Python :: 3.10
Classifier: Programming Language :: Python :: 3.11
Requires-Python: >=3.10,<3.12
License-File: LICENSE.md
Requires-Dist: fastapi >=0.112.2
Requires-Dist: uvicorn >=0.30.6
Requires-Dist: numpy >=1.26.3
Requires-Dist: pandas >=2.2.0
Requires-Dist: pillow >=10.2.0
Requires-Dist: python-multipart >=0.0.9
Requires-Dist: requests >=2.31.0
Requires-Dist: scikit-learn >=1.3.2
Requires-Dist: torch >=2.2.0
Requires-Dist: torchmetrics >=1.2.1
Requires-Dist: torchvision >=0.17.0
Requires-Dist: streamlit >=1.38.0
Requires-Dist: streamlit-navigation-bar
Requires-Dist: streamlit-extras
Requires-Dist: streamlit-toggle-switch
Requires-Dist: streamlit-ketcher
